cocoregman/__init__.py
cocoregman/__main__.py
cocoregman/errors.py
cocoregman/cli/__init__.py
cocoregman/cli/argp.py
cocoregman/cli/commands.py
cocoregman/core/__init__.py
cocoregman/core/env.py
cocoregman/core/orchestrator.py
cocoregman/core/runbook.py
cocoregman/core/schema.py
cocoregman/core/validation.py
cocoregman-1.2.0.dist-info/licenses/LICENSE
cocoregman-1.2.0.dist-info/METADATA
cocoregman-1.2.0.dist-info/WHEEL
cocoregman-1.2.0.dist-info/entry_points.txt
cocoregman-1.2.0.dist-info/top_level.txt
cocoregman-1.2.0.dist-info/RECORD
