Metadata-Version: 2.4
Name: cocoregman
Version: 1.2.0
Summary: Regression runner for cocotb-based verification workflows
Author: amutioalex
Maintainer: amutioalex
License-Expression: BSD-3-Clause
Project-URL: Homepage, https://www.github.com/amutioalex/cocoman
Project-URL: Repository, https://www.github.com/amutioalex/cocoman.git
Project-URL: Issues, https://github.com/amutioalex/cocoman/issues
Keywords: testbench,verification,cocotb,regression,runner
Classifier: Development Status :: 5 - Production/Stable
Classifier: Intended Audience :: Developers
Classifier: Natural Language :: English
Classifier: Operating System :: OS Independent
Classifier: Programming Language :: Python
Classifier: Programming Language :: Python :: 3
Classifier: Programming Language :: Python :: 3.9
Classifier: Programming Language :: Python :: 3.10
Classifier: Programming Language :: Python :: 3.11
Classifier: Programming Language :: Python :: 3.12
Classifier: Programming Language :: Python :: 3.13
Classifier: Framework :: cocotb
Classifier: Topic :: Scientific/Engineering :: Electronic Design Automation (EDA)
Requires-Python: >=3.9
License-File: LICENSE
Requires-Dist: cocotb<2
Requires-Dist: cerberus>=1.3
Requires-Dist: pyyaml>=6.0
Requires-Dist: rich>=14.1
Dynamic: license-file
